randwave/__init__.py
randwave/kernel_apply.py
randwave/kernel_fit.py
randwave/ravel.py
randwave/wavelet_fit.py
randwave/wavelets_base.py
randwave-0.2.1.dist-info/METADATA
randwave-0.2.1.dist-info/WHEEL
randwave-0.2.1.dist-info/top_level.txt
randwave-0.2.1.dist-info/zip-safe
randwave-0.2.1.dist-info/RECORD
