Metadata-Version: 2.1
Name: randwave
Version: 0.2.1
Summary: Random Wavelet Convolution
Home-page: https://github.com/fyancy/RaVEL
Author: Yong Feng
